d3tree/__init__.py
d3tree/cli.py
d3tree/html_template.py
d3tree/node.py
d3tree/utils.py
d3tree/templates/circles.html
d3tree/templates/flame.html
d3tree/templates/tree.html
d3tree/templates/treemap.html
d3tree-0.2.2.dist-info/LICENSE
d3tree-0.2.2.dist-info/METADATA
d3tree-0.2.2.dist-info/WHEEL
d3tree-0.2.2.dist-info/entry_points.txt
d3tree-0.2.2.dist-info/top_level.txt
d3tree-0.2.2.dist-info/RECORD
