Metadata-Version: 2.1
Name: d3tree
Version: 0.2.2
Summary: Visualizes file paths using D3.js
Home-page: https://github.com/dkreeft/d3tree
Author: Davey Kreeft
Classifier: Programming Language :: Python :: 3
Classifier: Development Status :: 3 - Alpha
Classifier: License :: OSI Approved :: MIT License
Classifier: Operating System :: OS Independent
Requires-Python: >=3.6
License-File: LICENSE
Requires-Dist: Click (>=7.0.0)
Provides-Extra: build
Requires-Dist: pytest ; extra == 'build'
Requires-Dist: pytest-cov ; extra == 'build'
Requires-Dist: setuptools (>=38.6.0) ; extra == 'build'
Requires-Dist: twine (>=1.11.0) ; extra == 'build'
Requires-Dist: wheel (>=0.31.0) ; extra == 'build'
Provides-Extra: dev
Requires-Dist: pytest ; extra == 'dev'
Requires-Dist: pytest-cov ; extra == 'dev'
